mypackage/__init__.py
conscious-0.0.0.dist-info/METADATA
conscious-0.0.0.dist-info/WHEEL
conscious-0.0.0.dist-info/top_level.txt
conscious-0.0.0.dist-info/RECORD
