Metadata-Version: 2.1
Name: conscious
Version: 0.0.0
Summary: Scheduled for public release in March by OpenConscious, Japan. 
Home-page: https://openconsciouss.com/
Author: Ami Tachibana
Author-email: tachibana@openconsc.com
Classifier: Programming Language :: Python :: 3
Classifier: License :: OSI Approved :: MIT License
Classifier: Operating System :: OS Independent
Requires-Python: >=3.6
